iris_stage/__init__.py
iris_stage/__main__.py
iris_stage/__version__.py
iris_stage/aws/__init__.py
iris_stage/aws/s3.py
iris_stage/aws/sqs.py
iris_stage/logs/__init__.py
iris_stage/logs/config.yaml
iris_stage/snap/__init__.py
iris_stage/snap/installer.py
iris_stage/srv/__init__.py
iris_stage/srv/srv.py
iris_stage-0.2.4.data/scripts/stage
iris_stage-0.2.4.data/scripts/unstage
iris_stage-0.2.4.dist-info/METADATA
iris_stage-0.2.4.dist-info/WHEEL
iris_stage-0.2.4.dist-info/top_level.txt
iris_stage-0.2.4.dist-info/RECORD
