Metadata-Version: 2.1
Name: iris-stage
Version: 0.2.4
Summary: Staging service for iris snap deployment pipeline
Home-page: https://github.com/Incuvers/iris-staging
Author: Incuvers
Author-email: info@incuvers.com
License: UNKNOWN
Download-URL: https://github.com/Incuvers/iris-stage/archive/0.0.1.tar.gz
Platform: UNKNOWN
Classifier: Topic :: Software Development :: Embedded Systems
Classifier: Topic :: Scientific/Engineering :: Bio-Informatics
Requires-Python: >=3.8.0
Requires-Dist: PyYAML (>=5.3.1)
Requires-Dist: boto3 (>=1.9.126)
Requires-Dist: service (>=0.6.0)
